nox/__init__.py
nox/__main__.py
nox/_cli.py
nox/_decorators.py
nox/_option_set.py
nox/_options.py
nox/_parametrize.py
nox/_resolver.py
nox/_typing.py
nox/_version.py
nox/command.py
nox/logger.py
nox/manifest.py
nox/popen.py
nox/project.py
nox/py.typed
nox/registry.py
nox/sessions.py
nox/tasks.py
nox/tox4_to_nox.jinja2
nox/tox_to_nox.py
nox/virtualenv.py
nox/workflow.py
nox-2025.11.12.dist-info/METADATA
nox-2025.11.12.dist-info/WHEEL
nox-2025.11.12.dist-info/entry_points.txt
nox-2025.11.12.dist-info/licenses/LICENSE
nox-2025.11.12.dist-info/RECORD
