Metadata-Version: 2.4
Name: nox
Version: 2025.11.12
Summary: Flexible test automation.
Project-URL: bug-tracker, https://github.com/wntrblm/nox/issues
Project-URL: documentation, https://nox.thea.codes
Project-URL: homepage, https://github.com/wntrblm/nox
Project-URL: repository, https://github.com/wntrblm/nox
Author-email: Alethea Katherine Flowers <me@thea.codes>
License-Expression: Apache-2.0
License-File: LICENSE
Keywords: automation,testing,tox
Classifier: Development Status :: 5 - Production/Stable
Classifier: Environment :: Console
Classifier: Intended Audience :: Developers
Classifier: Operating System :: MacOS
Classifier: Operating System :: Microsoft :: Windows
Classifier: Operating System :: POSIX
Classifier: Operating System :: Unix
Classifier: Programming Language :: Python
Classifier: Programming Language :: Python :: 3 :: Only
Classifier: Programming Language :: Python :: 3.8
Classifier: Programming Language :: Python :: 3.9
Classifier: Programming Language :: Python :: 3.10
Classifier: Programming Language :: Python :: 3.11
Classifier: Programming Language :: Python :: 3.12
Classifier: Programming Language :: Python :: 3.13
Classifier: Programming Language :: Python :: 3.14
Classifier: Topic :: Software Development :: Testing
Requires-Python: >=3.8
Requires-Dist: argcomplete<4,>=1.9.4
Requires-Dist: attrs>=24.1
Requires-Dist: colorlog<7,>=2.6.1
Requires-Dist: dependency-groups>=1.1
Requires-Dist: humanize>=4
Requires-Dist: packaging>=20.9; python_version < '3.10'
Requires-Dist: packaging>=21; python_version >= '3.10'
Requires-Dist: tomli>=1.1; python_version < '3.11'
Requires-Dist: virtualenv>=20.14.1; python_version < '3.10'
Requires-Dist: virtualenv>=20.15; python_version >= '3.10'
Provides-Extra: pbs
Requires-Dist: pbs-installer[all]>=2025.1.6; extra == 'pbs'
Provides-Extra: tox_to_nox
Requires-Dist: importlib-resources; (python_version < '3.9') and extra == 'tox_to_nox'
Requires-Dist: jinja2; extra == 'tox_to_nox'
Requires-Dist: tox>=4; extra == 'tox_to_nox'
Provides-Extra: uv
Requires-Dist: uv>=0.1.6; extra == 'uv'
